{
  "runId": "Ablation - Governance Mechanisms-treasury_stabilization_enabled=true_participation_target_rate=0_proposal_bond_fraction=0_01-run-929",
  "experimentName": "Ablation - Governance Mechanisms",
  "sweepValue": "treasury_stabilization_enabled=true_participation_target_rate=0_proposal_bond_fraction=0.01",
  "runIndex": 928,
  "config": {
    "num_developers": 0,
    "num_investors": 6,
    "num_traders": 4,
    "num_adaptive_investors": 4,
    "num_delegators": 46,
    "num_liquid_delegators": 12,
    "num_proposal_creators": 23,
    "num_validators": 0,
    "num_service_providers": 0,
    "num_arbitrators": 0,
    "num_regulators": 0,
    "num_auditors": 0,
    "num_bounty_hunters": 0,
    "num_external_partners": 0,
    "num_passive_members": 80,
    "num_artists": 0,
    "num_collectors": 0,
    "num_speculators": 4,
    "num_stakers": 10,
    "num_rl_traders": 0,
    "num_governance_experts": 19,
    "num_governance_whales": 0,
    "num_risk_managers": 0,
    "num_market_makers": 0,
    "num_whistleblowers": 2,
    "governance_rule": "majority",
    "governance_config": {
      "quorumPercentage": 0.05,
      "threshold": 0.5,
      "convictionThreshold": 0.1,
      "convictionHalfLife": 30
    },
    "token_emission_rate": 10,
    "token_burn_rate": 0,
    "staking_interest_rate": 0.03,
    "slash_fraction": 0,
    "reputation_decay_rate": 0.01,
    "market_shock_frequency": 0.05,
    "adaptive_learning_rate": 0.1,
    "adaptive_epsilon": 0.1,
    "violation_probability": 0.05,
    "reputation_penalty": 5,
    "comment_probability": 0.3,
    "voting_activity": 0.25,
    "external_partner_interact_probability": 0.1,
    "proposal_creation_probability": 0.004,
    "proposal_duration_min_steps": 24,
    "proposal_duration_max_steps": 96,
    "treasury_target_reserve": 10000,
    "treasury_target_reserve_fraction": 0.6,
    "treasury_buffer_fraction": 0.2,
    "treasury_buffer_fill_rate": 0.5,
    "treasury_emergency_topup_rate": 0.25,
    "treasury_max_spend_fraction": 0.15,
    "participation_boost_strength": 0.6,
    "participation_boost_decay": 0.1,
    "participation_boost_max": 0.25,
    "participation_inactivity_boost": 0.15,
    "participation_reward_per_vote": 0,
    "proposal_bond_min": 10,
    "proposal_bond_max": 1000,
    "proposal_inactivity_steps": 72,
    "proposal_temp_check_fraction": 0.25,
    "proposal_fast_track_min_steps": 6,
    "proposal_fast_track_approval": 0.6,
    "proposal_fast_track_quorum": 0.2,
    "vote_power_cap_fraction": 0.15,
    "vote_power_quadratic_threshold": 250,
    "vote_power_velocity_window": 72,
    "vote_power_velocity_penalty": 0.5,
    "delegation_lock_steps": 48,
    "treasury_stabilization_enabled": true,
    "participation_target_rate": 0,
    "proposal_bond_fraction": 0.01,
    "seed": 2130,
    "useIndexedDB": false
  },
  "seed": 2130,
  "metrics": {
    "Proposal Pass Rate": 0.8421052631578947,
    "Average Turnout": 0.14824275323033617,
    "Final Treasury": 10805.771280674011,
    "Final Token Price": 1.0328517182140236,
    "Final Member Count": 210,
    "Total Proposals": 21,
    "Quorum Reach Rate": 0.9523809523809523,
    "Avg Margin of Victory": 0.3416328973183614,
    "Avg Time to Decision": 1006.4736842105264,
    "Proposal Abandonment Rate": 0,
    "Proposal Rejection Rate": 0.15789473684210525,
    "Governance Overhead": 35.31578947368421,
    "Unique Voter Count": 172,
    "Voter Participation Rate": 0.15215419501133784,
    "Voter Concentration Gini": 0.39557873820168904,
    "Delegate Concentration": 0.24784233028979194,
    "Avg Votes Per Proposal": 31.952380952380953,
    "Voter Retention Rate": 0.832258064516129,
    "Voting Power Utilization": 0.1496249601900183,
    "Treasury Volatility": 0.21697800831500672,
    "Treasury Growth Rate": -0.7205619123191059,
    "Staking Participation": 0.0827861190232757,
    "Token Concentration Gini": 0.4804594071082078,
    "Avg Member Wealth": 116.11608874868872,
    "Wealth Mobility": 0.5195405928917922,
    "Whale Influence": 0.23446145303154375,
    "Whale Proposal Rate": 0.6666666666666666,
    "Governance Capture Risk": 0.2846829481684537,
    "Vote Buying Vulnerability": 158.2091765603599,
    "Single Entity Control": 0.037398912856665176,
    "Collusion Threshold": 0.18571428571428572,
    "Participation Trend": -0.002049616355738656,
    "Treasury Trend": -13.348054704665014,
    "Member Growth Rate": 0,
    "Proposal Rate": 1.05,
    "Governance Activity Index": 0.001421437121805174,
    "Final Gini": 0.48065118338690693,
    "Final Reputation Gini": 0.9622861892680352
  },
  "startedAt": "2026-02-13T17:27:58.133Z",
  "completedAt": "2026-02-13T17:28:03.584Z",
  "durationMs": 5451,
  "stepsCompleted": 2000
}