{
  "runId": "Academic Baseline-run-4877",
  "experimentName": "Academic Baseline",
  "runIndex": 4876,
  "config": {
    "num_developers": 0,
    "num_investors": 6,
    "num_traders": 4,
    "num_adaptive_investors": 4,
    "num_delegators": 46,
    "num_liquid_delegators": 12,
    "num_proposal_creators": 23,
    "num_validators": 0,
    "num_service_providers": 0,
    "num_arbitrators": 0,
    "num_regulators": 0,
    "num_auditors": 0,
    "num_bounty_hunters": 0,
    "num_external_partners": 0,
    "num_passive_members": 80,
    "num_artists": 0,
    "num_collectors": 0,
    "num_speculators": 4,
    "num_stakers": 10,
    "num_rl_traders": 0,
    "num_governance_experts": 19,
    "num_risk_managers": 0,
    "num_market_makers": 0,
    "num_whistleblowers": 2,
    "governance_rule": "majority",
    "governance_config": {
      "quorumPercentage": 0.05,
      "threshold": 0.5,
      "convictionThreshold": 0.1,
      "convictionHalfLife": 30
    },
    "token_emission_rate": 10,
    "token_burn_rate": 0,
    "staking_interest_rate": 0.03,
    "slash_fraction": 0,
    "reputation_decay_rate": 0.01,
    "market_shock_frequency": 0.05,
    "adaptive_learning_rate": 0.1,
    "adaptive_epsilon": 0.1,
    "violation_probability": 0.05,
    "reputation_penalty": 5,
    "comment_probability": 0.3,
    "voting_activity": 0.25,
    "external_partner_interact_probability": 0.1,
    "proposal_creation_probability": 0.004,
    "proposal_duration_min_steps": 24,
    "proposal_duration_max_steps": 96,
    "treasury_stabilization_enabled": true,
    "treasury_target_reserve": 10000,
    "treasury_target_reserve_fraction": 0.6,
    "treasury_buffer_fraction": 0.2,
    "treasury_buffer_fill_rate": 0.5,
    "treasury_emergency_topup_rate": 0.25,
    "treasury_max_spend_fraction": 0.15,
    "participation_target_rate": 0.2,
    "participation_boost_strength": 0.6,
    "participation_boost_decay": 0.1,
    "participation_boost_max": 0.25,
    "participation_inactivity_boost": 0.15,
    "participation_reward_per_vote": 0,
    "proposal_bond_fraction": 0.01,
    "proposal_bond_min": 10,
    "proposal_bond_max": 1000,
    "proposal_inactivity_steps": 72,
    "proposal_temp_check_fraction": 0.25,
    "proposal_fast_track_min_steps": 6,
    "proposal_fast_track_approval": 0.6,
    "proposal_fast_track_quorum": 0.2,
    "vote_power_cap_fraction": 0.15,
    "vote_power_quadratic_threshold": 250,
    "vote_power_velocity_window": 72,
    "vote_power_velocity_penalty": 0.5,
    "delegation_lock_steps": 48,
    "seed": 4918,
    "useIndexedDB": false
  },
  "seed": 4918,
  "metrics": {
    "Proposal Pass Rate": 0.025906735751295335,
    "Average Turnout": 0.033723458007921495,
    "Final Treasury": 11342.00140746371,
    "Final Token Price": 2.4949684687448457,
    "Final Member Count": 210,
    "Total Proposals": 196,
    "Quorum Reach Rate": 0.11224489795918367,
    "Avg Margin of Victory": 0.48810309060888185,
    "Avg Time to Decision": 1017.0155440414508,
    "Proposal Abandonment Rate": 0,
    "Proposal Rejection Rate": 0.9740932642487047,
    "Governance Overhead": 6.191709844559585,
    "Unique Voter Count": 144,
    "Voter Participation Rate": 0.029033041788143817,
    "Voter Concentration Gini": 0.4931540147439729,
    "Delegate Concentration": 0.4122258976418309,
    "Avg Votes Per Proposal": 6.096938775510204,
    "Voter Retention Rate": 0.9929078014184397,
    "Voting Power Utilization": 0.0349109802494169,
    "Treasury Volatility": 0.22554123617527327,
    "Treasury Growth Rate": -0.7422738488201214,
    "Staking Participation": 0.09144136217557466,
    "Token Concentration Gini": 0.5246392775609617,
    "Avg Member Wealth": 104.85735224922865,
    "Wealth Mobility": 0.47536072243903826,
    "Whale Influence": 0.6078720418968141,
    "Whale Proposal Rate": 0.08673469387755102,
    "Governance Capture Risk": 0.4132468985174741,
    "Vote Buying Vulnerability": 62.36810336070485,
    "Single Entity Control": 0.03845612695338623,
    "Collusion Threshold": 0.16666666666666666,
    "Participation Trend": 0.00005819202634838634,
    "Treasury Trend": -9.949226110282076,
    "Member Growth Rate": 0,
    "Proposal Rate": 9.8,
    "Governance Activity Index": 0.003368909594068732,
    "Final Gini": 0.5246383542268962,
    "Final Reputation Gini": 0.9754527440179777
  },
  "startedAt": "2026-02-06T13:21:04.998Z",
  "completedAt": "2026-02-06T13:21:08.865Z",
  "durationMs": 3867,
  "stepsCompleted": 2000
}