{
  "runId": "Academic Baseline-run-1854",
  "experimentName": "Academic Baseline",
  "runIndex": 1853,
  "config": {
    "num_developers": 0,
    "num_investors": 6,
    "num_traders": 4,
    "num_adaptive_investors": 4,
    "num_delegators": 46,
    "num_liquid_delegators": 12,
    "num_proposal_creators": 23,
    "num_validators": 0,
    "num_service_providers": 0,
    "num_arbitrators": 0,
    "num_regulators": 0,
    "num_auditors": 0,
    "num_bounty_hunters": 0,
    "num_external_partners": 0,
    "num_passive_members": 80,
    "num_artists": 0,
    "num_collectors": 0,
    "num_speculators": 4,
    "num_stakers": 10,
    "num_rl_traders": 0,
    "num_governance_experts": 19,
    "num_risk_managers": 0,
    "num_market_makers": 0,
    "num_whistleblowers": 2,
    "governance_rule": "majority",
    "governance_config": {
      "quorumPercentage": 0.05,
      "threshold": 0.5,
      "convictionThreshold": 0.1,
      "convictionHalfLife": 30
    },
    "token_emission_rate": 10,
    "token_burn_rate": 0,
    "staking_interest_rate": 0.03,
    "slash_fraction": 0,
    "reputation_decay_rate": 0.01,
    "market_shock_frequency": 0.05,
    "adaptive_learning_rate": 0.1,
    "adaptive_epsilon": 0.1,
    "violation_probability": 0.05,
    "reputation_penalty": 5,
    "comment_probability": 0.3,
    "voting_activity": 0.25,
    "external_partner_interact_probability": 0.1,
    "proposal_creation_probability": 0.004,
    "proposal_duration_min_steps": 24,
    "proposal_duration_max_steps": 96,
    "treasury_stabilization_enabled": true,
    "treasury_target_reserve": 10000,
    "treasury_target_reserve_fraction": 0.6,
    "treasury_buffer_fraction": 0.2,
    "treasury_buffer_fill_rate": 0.5,
    "treasury_emergency_topup_rate": 0.25,
    "treasury_max_spend_fraction": 0.15,
    "participation_target_rate": 0.2,
    "participation_boost_strength": 0.6,
    "participation_boost_decay": 0.1,
    "participation_boost_max": 0.25,
    "participation_inactivity_boost": 0.15,
    "participation_reward_per_vote": 0,
    "proposal_bond_fraction": 0.01,
    "proposal_bond_min": 10,
    "proposal_bond_max": 1000,
    "proposal_inactivity_steps": 72,
    "proposal_temp_check_fraction": 0.25,
    "proposal_fast_track_min_steps": 6,
    "proposal_fast_track_approval": 0.6,
    "proposal_fast_track_quorum": 0.2,
    "vote_power_cap_fraction": 0.15,
    "vote_power_quadratic_threshold": 250,
    "vote_power_velocity_window": 72,
    "vote_power_velocity_penalty": 0.5,
    "delegation_lock_steps": 48,
    "seed": 1895,
    "useIndexedDB": false
  },
  "seed": 1895,
  "metrics": {
    "Proposal Pass Rate": 0.045454545454545456,
    "Average Turnout": 0.04686177404606711,
    "Final Treasury": 12027.68188118573,
    "Final Token Price": 1.3016556505868915,
    "Final Member Count": 210,
    "Total Proposals": 201,
    "Quorum Reach Rate": 0.16417910447761194,
    "Avg Margin of Victory": 0.48238667982620353,
    "Avg Time to Decision": 1089.7474747474748,
    "Proposal Abandonment Rate": 0,
    "Proposal Rejection Rate": 0.9545454545454546,
    "Governance Overhead": 8.252525252525253,
    "Unique Voter Count": 146,
    "Voter Participation Rate": 0.038711205875384964,
    "Voter Concentration Gini": 0.44096287229702164,
    "Delegate Concentration": 0.3307661946804257,
    "Avg Votes Per Proposal": 8.129353233830846,
    "Voter Retention Rate": 0.9794520547945206,
    "Voting Power Utilization": 0.04903588739975368,
    "Treasury Volatility": 0.23783905899246136,
    "Treasury Growth Rate": -0.7064821397985641,
    "Staking Participation": 0.10078314577792612,
    "Token Concentration Gini": 0.47716840623340406,
    "Avg Member Wealth": 95.13792261377883,
    "Wealth Mobility": 0.5228315937665959,
    "Whale Influence": 0.5765863038392051,
    "Whale Proposal Rate": 0.11940298507462686,
    "Governance Capture Risk": 0.3415748374803715,
    "Vote Buying Vulnerability": 64.06078087647177,
    "Single Entity Control": 0.02949452166083449,
    "Collusion Threshold": 0.21904761904761905,
    "Participation Trend": -0.00015658096392252608,
    "Treasury Trend": -14.942863303730244,
    "Member Growth Rate": 0,
    "Proposal Rate": 10.05,
    "Governance Activity Index": 0.0048545528525756115,
    "Final Gini": 0.47672603389225676,
    "Final Reputation Gini": 0.9734350712338469
  },
  "startedAt": "2026-02-06T12:31:41.414Z",
  "completedAt": "2026-02-06T12:31:45.458Z",
  "durationMs": 4044,
  "stepsCompleted": 2000
}