{
  "runId": "Calibration - Participation Dynamics-voting_activity=0_25_participation_target_rate=0-run-661",
  "experimentName": "Calibration - Participation Dynamics",
  "sweepValue": "voting_activity=0.25_participation_target_rate=0",
  "runIndex": 660,
  "config": {
    "num_developers": 0,
    "num_investors": 6,
    "num_traders": 4,
    "num_adaptive_investors": 4,
    "num_delegators": 46,
    "num_liquid_delegators": 12,
    "num_proposal_creators": 23,
    "num_validators": 0,
    "num_service_providers": 0,
    "num_arbitrators": 0,
    "num_regulators": 0,
    "num_auditors": 0,
    "num_bounty_hunters": 0,
    "num_external_partners": 0,
    "num_passive_members": 80,
    "num_artists": 0,
    "num_collectors": 0,
    "num_speculators": 4,
    "num_stakers": 10,
    "num_rl_traders": 0,
    "num_governance_experts": 19,
    "num_governance_whales": 0,
    "num_risk_managers": 0,
    "num_market_makers": 0,
    "num_whistleblowers": 2,
    "governance_rule": "majority",
    "governance_config": {
      "quorumPercentage": 0.05,
      "threshold": 0.5,
      "convictionThreshold": 0.1,
      "convictionHalfLife": 30
    },
    "token_emission_rate": 10,
    "token_burn_rate": 0,
    "staking_interest_rate": 0.03,
    "slash_fraction": 0,
    "reputation_decay_rate": 0.01,
    "market_shock_frequency": 0.05,
    "adaptive_learning_rate": 0.1,
    "adaptive_epsilon": 0.1,
    "violation_probability": 0.05,
    "reputation_penalty": 5,
    "comment_probability": 0.3,
    "voting_activity": 0.25,
    "external_partner_interact_probability": 0.1,
    "proposal_creation_probability": 0.004,
    "proposal_duration_min_steps": 24,
    "proposal_duration_max_steps": 96,
    "treasury_stabilization_enabled": true,
    "treasury_target_reserve": 10000,
    "treasury_target_reserve_fraction": 0.6,
    "treasury_buffer_fraction": 0.2,
    "participation_boost_strength": 0.6,
    "participation_boost_decay": 0.1,
    "participation_boost_max": 0.25,
    "participation_inactivity_boost": 0.15,
    "participation_reward_per_vote": 0,
    "proposal_bond_fraction": 0.01,
    "proposal_bond_min": 10,
    "proposal_bond_max": 1000,
    "proposal_inactivity_steps": 72,
    "vote_power_cap_fraction": 0.15,
    "vote_power_quadratic_threshold": 250,
    "vote_power_velocity_window": 72,
    "vote_power_velocity_penalty": 0.5,
    "delegation_lock_steps": 48,
    "participation_target_rate": 0,
    "seed": 3761,
    "useIndexedDB": false
  },
  "seed": 3761,
  "metrics": {
    "Proposal Pass Rate": 0.7777777777777778,
    "Average Turnout": 0.14661296857498662,
    "Final Treasury": 10423.92309772078,
    "Final Token Price": 0.9505669215106841,
    "Final Member Count": 210,
    "Total Proposals": 27,
    "Quorum Reach Rate": 1,
    "Avg Margin of Victory": 0.29289267267623065,
    "Avg Time to Decision": 898.4074074074074,
    "Proposal Abandonment Rate": 0,
    "Proposal Rejection Rate": 0.2222222222222222,
    "Governance Overhead": 32.74074074074074,
    "Unique Voter Count": 173,
    "Voter Participation Rate": 0.15590828924162262,
    "Voter Concentration Gini": 0.3834733893557423,
    "Delegate Concentration": 0.2614682476672309,
    "Avg Votes Per Proposal": 32.74074074074074,
    "Voter Retention Rate": 0.9030303030303031,
    "Voting Power Utilization": 0.1474711226404924,
    "Treasury Volatility": 0.23267589370713773,
    "Treasury Growth Rate": -0.7178891855974393,
    "Staking Participation": 0.07873583190377755,
    "Token Concentration Gini": 0.5055089592016233,
    "Avg Member Wealth": 122.83323174638463,
    "Wealth Mobility": 0.4944910407983767,
    "Whale Influence": 0.2603119945606886,
    "Whale Proposal Rate": 0.8148148148148148,
    "Governance Capture Risk": 0.2744296048555843,
    "Vote Buying Vulnerability": 105.51576603352584,
    "Single Entity Control": 0.03835147254237777,
    "Collusion Threshold": 0.1523809523809524,
    "Participation Trend": 0.00032831338354147055,
    "Treasury Trend": -13.599003466843241,
    "Member Growth Rate": 0,
    "Proposal Rate": 1.35,
    "Governance Activity Index": 0.0019908601556466467,
    "Final Gini": 0.5055052979970032,
    "Final Reputation Gini": 0.9707844042845111
  },
  "startedAt": "2026-02-13T15:44:50.783Z",
  "completedAt": "2026-02-13T15:44:56.623Z",
  "durationMs": 5840,
  "stepsCompleted": 2000
}