{
  "runId": "Calibration - Participation Dynamics-voting_activity=0_25_participation_target_rate=0_15-run-276",
  "experimentName": "Calibration - Participation Dynamics",
  "sweepValue": "voting_activity=0.25_participation_target_rate=0.15",
  "runIndex": 275,
  "config": {
    "num_developers": 0,
    "num_investors": 6,
    "num_traders": 4,
    "num_adaptive_investors": 4,
    "num_delegators": 46,
    "num_liquid_delegators": 12,
    "num_proposal_creators": 23,
    "num_validators": 0,
    "num_service_providers": 0,
    "num_arbitrators": 0,
    "num_regulators": 0,
    "num_auditors": 0,
    "num_bounty_hunters": 0,
    "num_external_partners": 0,
    "num_passive_members": 80,
    "num_artists": 0,
    "num_collectors": 0,
    "num_speculators": 4,
    "num_stakers": 10,
    "num_rl_traders": 0,
    "num_governance_experts": 19,
    "num_governance_whales": 0,
    "num_risk_managers": 0,
    "num_market_makers": 0,
    "num_whistleblowers": 2,
    "governance_rule": "majority",
    "governance_config": {
      "quorumPercentage": 0.05,
      "threshold": 0.5,
      "convictionThreshold": 0.1,
      "convictionHalfLife": 30
    },
    "token_emission_rate": 10,
    "token_burn_rate": 0,
    "staking_interest_rate": 0.03,
    "slash_fraction": 0,
    "reputation_decay_rate": 0.01,
    "market_shock_frequency": 0.05,
    "adaptive_learning_rate": 0.1,
    "adaptive_epsilon": 0.1,
    "violation_probability": 0.05,
    "reputation_penalty": 5,
    "comment_probability": 0.3,
    "voting_activity": 0.25,
    "external_partner_interact_probability": 0.1,
    "proposal_creation_probability": 0.004,
    "proposal_duration_min_steps": 24,
    "proposal_duration_max_steps": 96,
    "treasury_stabilization_enabled": true,
    "treasury_target_reserve": 10000,
    "treasury_target_reserve_fraction": 0.6,
    "treasury_buffer_fraction": 0.2,
    "participation_boost_strength": 0.6,
    "participation_boost_decay": 0.1,
    "participation_boost_max": 0.25,
    "participation_inactivity_boost": 0.15,
    "participation_reward_per_vote": 0,
    "proposal_bond_fraction": 0.01,
    "proposal_bond_min": 10,
    "proposal_bond_max": 1000,
    "proposal_inactivity_steps": 72,
    "vote_power_cap_fraction": 0.15,
    "vote_power_quadratic_threshold": 250,
    "vote_power_velocity_window": 72,
    "vote_power_velocity_penalty": 0.5,
    "delegation_lock_steps": 48,
    "participation_target_rate": 0.15,
    "seed": 4376,
    "useIndexedDB": false
  },
  "seed": 4376,
  "metrics": {
    "Proposal Pass Rate": 0.8636363636363636,
    "Average Turnout": 0.2765306333923248,
    "Final Treasury": 12027.220441277717,
    "Final Token Price": 16.667531468639048,
    "Final Member Count": 210,
    "Total Proposals": 23,
    "Quorum Reach Rate": 1,
    "Avg Margin of Victory": 0.30370837397652717,
    "Avg Time to Decision": 1233.1363636363637,
    "Proposal Abandonment Rate": 0,
    "Proposal Rejection Rate": 0.13636363636363635,
    "Governance Overhead": 44.54545454545455,
    "Unique Voter Count": 168,
    "Voter Participation Rate": 0.20289855072463767,
    "Voter Concentration Gini": 0.38277939747327505,
    "Delegate Concentration": 0.20154519246481808,
    "Avg Votes Per Proposal": 42.608695652173914,
    "Voter Retention Rate": 0.9119496855345912,
    "Voting Power Utilization": 0.28303969212013436,
    "Treasury Volatility": 0.2680314964884104,
    "Treasury Growth Rate": -0.7204462028473654,
    "Staking Participation": 0.12593041152868964,
    "Token Concentration Gini": 0.33019724425108204,
    "Avg Member Wealth": 76.6877691235947,
    "Wealth Mobility": 0.6698027557489179,
    "Whale Influence": 0.19529007276342902,
    "Whale Proposal Rate": 0,
    "Governance Capture Risk": 0.21899624245442922,
    "Vote Buying Vulnerability": 151.8481884944482,
    "Single Entity Control": 0.01323634640801769,
    "Collusion Threshold": 0.3333333333333333,
    "Participation Trend": 0.0016564696122994928,
    "Treasury Trend": -19.407136077265715,
    "Member Growth Rate": 0,
    "Proposal Rate": 1.15,
    "Governance Activity Index": 0.003113436613321477,
    "Final Gini": 0.33016258622587924,
    "Final Reputation Gini": 0.9901318718534475
  },
  "startedAt": "2026-02-13T15:53:34.831Z",
  "completedAt": "2026-02-13T15:53:41.764Z",
  "durationMs": 6933,
  "stepsCompleted": 2000
}