{
  "runId": "Sensitivity - Quorum Threshold-0_25-run-019",
  "experimentName": "Sensitivity - Quorum Threshold",
  "sweepValue": 0.25,
  "runIndex": 18,
  "config": {
    "num_developers": 0,
    "num_investors": 6,
    "num_traders": 4,
    "num_adaptive_investors": 4,
    "num_delegators": 46,
    "num_liquid_delegators": 12,
    "num_proposal_creators": 23,
    "num_validators": 0,
    "num_service_providers": 0,
    "num_arbitrators": 0,
    "num_regulators": 0,
    "num_auditors": 0,
    "num_bounty_hunters": 0,
    "num_external_partners": 0,
    "num_passive_members": 80,
    "num_artists": 0,
    "num_collectors": 0,
    "num_speculators": 4,
    "num_stakers": 10,
    "num_rl_traders": 0,
    "num_governance_experts": 19,
    "num_governance_whales": 0,
    "num_risk_managers": 0,
    "num_market_makers": 0,
    "num_whistleblowers": 2,
    "governance_rule": "majority",
    "governance_config": {
      "quorumPercentage": 0.25,
      "threshold": 0.5,
      "convictionThreshold": 0.1,
      "convictionHalfLife": 30
    },
    "token_emission_rate": 10,
    "token_burn_rate": 0,
    "staking_interest_rate": 0.03,
    "slash_fraction": 0,
    "reputation_decay_rate": 0.01,
    "market_shock_frequency": 0.05,
    "adaptive_learning_rate": 0.1,
    "adaptive_epsilon": 0.1,
    "violation_probability": 0.05,
    "reputation_penalty": 5,
    "comment_probability": 0.3,
    "voting_activity": 0.25,
    "external_partner_interact_probability": 0.1,
    "proposal_creation_probability": 0.004,
    "proposal_duration_min_steps": 24,
    "proposal_duration_max_steps": 96,
    "treasury_stabilization_enabled": true,
    "treasury_target_reserve": 10000,
    "treasury_target_reserve_fraction": 0.6,
    "treasury_buffer_fraction": 0.2,
    "treasury_buffer_fill_rate": 0.5,
    "treasury_emergency_topup_rate": 0.25,
    "treasury_max_spend_fraction": 0.15,
    "participation_target_rate": 0.2,
    "participation_boost_strength": 0.6,
    "participation_boost_decay": 0.1,
    "participation_boost_max": 0.25,
    "participation_inactivity_boost": 0.15,
    "participation_reward_per_vote": 0,
    "proposal_bond_fraction": 0.01,
    "proposal_bond_min": 10,
    "proposal_bond_max": 1000,
    "proposal_inactivity_steps": 72,
    "proposal_temp_check_fraction": 0.25,
    "proposal_fast_track_min_steps": 6,
    "proposal_fast_track_approval": 0.6,
    "proposal_fast_track_quorum": 0.2,
    "vote_power_cap_fraction": 0.15,
    "vote_power_quadratic_threshold": 250,
    "vote_power_velocity_window": 72,
    "vote_power_velocity_penalty": 0.5,
    "delegation_lock_steps": 48,
    "seed": 821,
    "useIndexedDB": false
  },
  "seed": 821,
  "metrics": {
    "Proposal Pass Rate": 0.9767441860465116,
    "Average Turnout": 0.24465162538683544,
    "Final Treasury": 12048.20133051302,
    "Final Token Price": 3.0950335198582732,
    "Final Member Count": 405,
    "Total Proposals": 43,
    "Quorum Reach Rate": 0.11627906976744186,
    "Avg Margin of Victory": 0.5157769689782833,
    "Avg Time to Decision": 1028.2093023255813,
    "Proposal Abandonment Rate": 0,
    "Proposal Rejection Rate": 0.023255813953488372,
    "Governance Overhead": 69.6046511627907,
    "Unique Voter Count": 330,
    "Voter Participation Rate": 0.23426543740491398,
    "Voter Concentration Gini": 0.4223225430154564,
    "Delegate Concentration": 0.2850164707446829,
    "Avg Votes Per Proposal": 69.6046511627907,
    "Voter Retention Rate": 0.8987854251012146,
    "Voting Power Utilization": 0.1813304109646175,
    "Treasury Volatility": 0.25894679913679663,
    "Treasury Growth Rate": -0.720097041607557,
    "Staking Participation": 0.08424877045563661,
    "Token Concentration Gini": 0.4345644146836359,
    "Avg Member Wealth": 112.55004667959359,
    "Wealth Mobility": 0.5654355853163642,
    "Whale Influence": 0.28427272712070023,
    "Whale Proposal Rate": 0.6744186046511628,
    "Governance Capture Risk": 0.2849030389867362,
    "Vote Buying Vulnerability": 47.860393491535206,
    "Single Entity Control": 0.020386771632315108,
    "Collusion Threshold": 0.34074074074074073,
    "Participation Trend": 0.0031861972156332755,
    "Treasury Trend": -15.157893859688077,
    "Member Growth Rate": 0.9285714285714286,
    "Proposal Rate": 2.15,
    "Governance Activity Index": 0.0038986038357392764,
    "Final Gini": 0.43453391978477307,
    "Final Reputation Gini": 0.9874516227428523
  },
  "startedAt": "2026-02-21T15:54:56.207Z",
  "completedAt": "2026-02-21T15:55:17.348Z",
  "durationMs": 21141,
  "stepsCompleted": 2000
}